{
  "business_id": "f3fbc652-2582-4c45-b279-188dfcb484fc",
  "address_id": "cb09c8fe-f2d1-4979-bdf9-2783aeefd759",
  "delivery_address_id": "cb09c8fe-f2d1-4979-bdf9-2783aeefd759",
  "finance_id": "ab88cc5d-2f88-438f-9fa2-4b9eb2f2df5e",
  "type": "MERCHANT",
  "is_business_unit": false,
  "business_group_name": null,
  "name": "Stracke Inc",
  "description": "Stand-alone zero defect application",
  "tax_id": "98733321",
  "registration_id": "33341",
  "email": "Letha_Stehr68@hotmail.com",
  "telephone": "+00050609447",
  "telephone_code": "SI",
  "telephone_number": "050609447",
  "website_url": "https://shabby-understanding.biz",
  "working_hours": {
    "fri": [
      [
        "10:00",
        "23:00"
      ]
    ],
    "mon": [
      [
        "10:00",
        "22:00"
      ]
    ],
    "sat": [
      [
        "10:00",
        "23:00"
      ]
    ],
    "sun": [
      [
        "10:00",
        "22:00"
      ]
    ],
    "thu": [
      [
        "10:00",
        "22:00"
      ]
    ],
    "tue": [
      [
        "10:00",
        "22:00"
      ]
    ],
    "wed": [
      [
        "10:00",
        "22:00"
      ]
    ],
    "holidays": [
      [
        "10:00",
        "22:00"
      ]
    ]
  },
  "seats": 15,
  "minimum_order": 20,
  "offers_daily_meals": false,
  "popular": true,
  "new": true,
  "created_at": "2025-03-13T13:02:14.792Z",
  "updated_at": "2025-03-13T13:02:18.370Z",
  "parent_business_id": null,
  "reviewable_id": null,
  "stripe_account_id": "acct_1R2BQLIOZTiUmKT7",
  "stripe_customer_id": "cus_Rw3XEwkGmPMmLk",
  "word_buy_stripe_product_id": null,
  "word_buy_stripe_subscription_id": null,
  "daily_users_sorted": [],
  "daily_users_sorting_type": "AUTOMATIC",
  "restaurant_overwhelmed": false,
  "activated_at": null,
  "sales_representative_id": null,
  "address": {
    "address_id": "cb09c8fe-f2d1-4979-bdf9-2783aeefd759",
    "address": "83450 Bedford Road",
    "latitude": "46.044945466785975",
    "longitude": "14.47113090284727",
    "street": null,
    "house_number": null,
    "city": null,
    "country": null,
    "postal": null
  },
  "delivery_address": {
    "address_id": "cb09c8fe-f2d1-4979-bdf9-2783aeefd759",
    "address": "83450 Bedford Road",
    "latitude": "46.044945466785975",
    "longitude": "14.47113090284727",
    "street": null,
    "house_number": null,
    "city": null,
    "country": null,
    "postal": null
  },
  "word_buys": [],
  "menus": [
    {
      "menu_id": "c7c1d3f4-2e2b-420e-9178-d7d01bd41904",
      "business_id": "f3fbc652-2582-4c45-b279-188dfcb484fc",
      "active": true,
      "menu_categories_ordered": null,
      "isDailyMeal": false,
      "date": null,
      "categories": []
    }
  ],
  "documents": [
    {
      "document_id": "a610145f-8459-4ac8-9dc9-6ac4e419a8b6",
      "document_type": "LOGO",
      "created_at": "2025-03-13T13:02:15.675Z",
      "updated_at": "2025-03-13T13:02:15.964Z",
      "expiration_date": null,
      "issue_date": null,
      "additional_info": null,
      "public": true,
      "driver_id": null,
      "delivery_driver_id": null,
      "business_id": "f3fbc652-2582-4c45-b279-188dfcb484fc",
      "user_id": null,
      "vehicle_id": null,
      "menu_item_id": null,
      "lost_item_id": null,
      "transaction_id": null,
      "files": [
        {
          "file_id": "3f41e7c0-63c4-44bc-811e-836ff68a1dd1",
          "url": "https://s3.tebi.io/klikni-test/3f41e7c0-63c4-44bc-811e-836ff68a1dd1.jpeg",
          "file_type": "IMAGE",
          "public": true,
          "mime_type": "image/jpeg",
          "created_at": "2025-03-13T13:02:15.689Z",
          "updated_at": "2025-03-13T13:02:15.962Z",
          "document_id": "a610145f-8459-4ac8-9dc9-6ac4e419a8b6"
        }
      ]
    },
    {
      "document_id": "55cec360-ed61-47a5-a696-c87a7d508804",
      "document_type": "BANNER",
      "created_at": "2025-03-13T13:02:15.967Z",
      "updated_at": "2025-03-13T13:02:16.058Z",
      "expiration_date": null,
      "issue_date": null,
      "additional_info": null,
      "public": true,
      "driver_id": null,
      "delivery_driver_id": null,
      "business_id": "f3fbc652-2582-4c45-b279-188dfcb484fc",
      "user_id": null,
      "vehicle_id": null,
      "menu_item_id": null,
      "lost_item_id": null,
      "transaction_id": null,
      "files": [
        {
          "file_id": "9c3bf952-17aa-4e7e-a5d7-79194820ac02",
          "url": "https://s3.tebi.io/klikni-test/9c3bf952-17aa-4e7e-a5d7-79194820ac02.jpeg",
          "file_type": "IMAGE",
          "public": true,
          "mime_type": "image/jpeg",
          "created_at": "2025-03-13T13:02:15.968Z",
          "updated_at": "2025-03-13T13:02:16.055Z",
          "document_id": "55cec360-ed61-47a5-a696-c87a7d508804"
        }
      ]
    }
  ],
  "promo_sections": []
}